nsys2prv/EventWriter.py
nsys2prv/NSYSInterface.py
nsys2prv/__init__.py
nsys2prv/parse_nsys_stats.py
nsys2prv/scripts/graph_cupti.sql
nsys2prv/scripts/graph_events.sql
nsys2prv/scripts/graph_node.sql
nsys2prv/scripts/kernels.sql
nsys2prv/scripts/memcpy.sql
nsys2prv/scripts/memset.sql
nsys2prv/scripts/mpi_coll.sql
nsys2prv/scripts/mpi_io.sql
nsys2prv/scripts/mpi_other.sql
nsys2prv/scripts/mpi_p2p.sql
nsys2prv/scripts/nvtx_pushpop_simple.sql
nsys2prv/scripts/nvtx_pushpop_trace.sql
nsys2prv/scripts/nvtx_pushpop_trace_prepare.sql
nsys2prv/scripts/nvtx_startend_trace.sql
nsys2prv/scripts/openacc-test.sql
nsys2prv/scripts/openacc_data.sql
nsys2prv/scripts/openacc_launch.sql
nsys2prv/scripts/openacc_other.sql
nsys2prv/semantics/__init__.py
nsys2prv/semantics/cuda_graphs_semantic.py
nsys2prv/semantics/gpu_metrics_semantic.py
nsys2prv/semantics/kernels_semantic.py
nsys2prv/semantics/mpi_event_encoding.py
nsys2prv/semantics/mpi_semantic.py
nsys2prv/semantics/nsys_event.py
nsys2prv/semantics/nvtx_pushpop_semantic.py
nsys2prv/semantics/nvtx_pushpop_simple_semantic.py
nsys2prv/semantics/nvtx_startend_semantic.py
nsys2prv/semantics/openacc_semantic.py
nsys2prv-0.5.8.dist-info/LICENSE
nsys2prv-0.5.8.dist-info/METADATA
nsys2prv-0.5.8.dist-info/WHEEL
nsys2prv-0.5.8.dist-info/entry_points.txt
nsys2prv-0.5.8.dist-info/RECORD
