Metadata-Version: 2.3
Name: nsys2prv
Version: 0.5.8
Summary: Translate a NVIDIA Nsight System trace to a Paraver trace
License: GPL-3.0-only
Author: Marc Clascà
Author-email: marc.clasca@bsc.es
Requires-Python: >=3.10,<4.0
Classifier: License :: OSI Approved :: GNU General Public License v3 (GPLv3)
Classifier: Programming Language :: Python :: 3
Classifier: Programming Language :: Python :: 3.10
Classifier: Programming Language :: Python :: 3.11
Classifier: Programming Language :: Python :: 3.12
Classifier: Programming Language :: Python :: 3.13
Requires-Dist: pandas (>=2.2.2,<3.0.0)
Requires-Dist: sqlalchemy (>=2.0.0,<3.0.0)
Requires-Dist: tqdm
Project-URL: Homepage, https://pm.bsc.es/gitlab/beppp/nsys2prv
Project-URL: Repository, https://pm.bsc.es/gitlab/beppp/nsys2prv
